<?xml version="1.0" encoding="UTF-8"?>
<standard-document xmlns="http://riboseinc.com/isoxml">
<bibdata type="article"> 
   
   
   
   
  <language>en</language> 
  <script>Latn</script> 
  <status format="plain">published</status> 
  <copyright> 
    <from>2019</from> 
  </copyright> 
  <editorialgroup> 
    <technical-committee/> 
  </editorialgroup> 
</bibdata>
<sections> 
  <example id="/req/geojson/content"><example id="_b1057658-c56b-467b-9cb3-599c433d9e0e"><dl id="_928703ce-c208-4e10-8933-15639e922e30">    
  <dt>response</dt>    
  <dd>    
    <p id="_439b5830-62ec-4763-ae2c-c346803d5fbe">200</p>    
  </dd>    
  <dt>media-type</dt>    
  <dd>    
    <p id="_2263296a-1080-4219-a0cd-78c44b212f81">application/geo+json</p>    
  </dd>    
</dl>   
<p id="_0da64d81-21ab-41c6-9f54-013cf30275a7">Every <tt>200</tt>-response with the media type <tt>application/geo+json</tt> SHALL be</p>   
<ul id="_b4689d6d-60c3-4afe-81a5-49656d5ccd0a">    
  <li>    
    <p id="_c264cdba-444a-41a8-bf83-4141cde05178">a <link target="https://tools.ietf.org/html/rfc7946#section-3.3">GeoJSON FeatureCollection Object</link> for feature collections, and</p>    
  </li>    
  <li>    
    <p id="_da899bde-bb0d-41dd-a4d0-05f8c73f3b2a">a <link target="https://tools.ietf.org/html/rfc7946#section-3.2">GeoJSON Feature Object</link> for features.</p>    
  </li>    
</ul></example>  
<p id="_8dc64e3a-d2d3-4a39-96bd-d4abf8256057">The links specified in the requirements <xref target="requirement:&quot;/req/core/fc-links&quot;"/> and   
<xref target="requirement:&quot;/req/core/f-links&quot;"/> SHALL be added in a extension property   
(foreign member) with the name <tt>links</tt>.</p>  
<p id="_674330d0-07e8-4153-b423-e94e6b7f2ae7">The schema of all responses with the media type <tt>application/json</tt> SHALL   
conform with the JSON Schema specified for the resource in the requirements class   
<xref target="rc_core">WFS 3.0 Core</xref>.</p></example> 
</sections>
</standard-document>
